{
    "$schema": "https://schema.management.azure.com/schemas/2015-01-01/deploymentParameters.json#",
    "contentVersion": "1.0.0.0",
    "parameters": {
        "windowsVirtualMachineName": {
            "value": "winjb"
        },
        "linuxVirtualMachineName": {
            "value": "linuxjb"
        },
        "workspaceId": {
            "value": ""
        },
        "logAnalyticsWorkspacePrimarySharedKey": {
            "value": ""
        },
        "artifactsStorageAccountKey": {
            "value": ""
        },
        "artifactsStorageAccountName": {
            "value": ""
        },
        "vNetId": {
            "value": ""
        },
        "jumpboxAsgId": {
            "value": ""
        },
        "subnetName": {
            "value": ""
        },
        "adminUsername": {
            "value": ""
        },
        "adminPassword": {
            "value": ""
        },
        "windowsVirtualMachineCount": {
            "value": 1
        },
        "windowsVirtualMachineSize": {
            "value": "Standard_DS2_v2"
        },
        "windowsOSImage": {
            "value": {
                "offer": "WindowsServer",
                "publisher": "MicrosoftWindowsServer",
                "sku": "2016-Datacenter"
            }
        },
        "linuxVirtualMachineCount": {
            "value": 1
        },
        "linuxVirtualMachineSize": {
            "value": "Standard_D2s_v3"
        },
        "linuxOSImage": {
            "value": {
                "publisher": "Canonical",
                "offer": "UbuntuServer",
                "sku": "18.04-LTS",
                "version": "latest"
            }
        },
        "diagnosticsStorageAccountName": {
            "value": ""
        },
        "diagnosticsStorageAccountSasToken": {
            "value": ""
        }
    }
}